RecFeatureSelect/__init__.py
RecFeatureSelect/_main.py
RecFeatureSelect-0.3.1.dist-info/LICENSE
RecFeatureSelect-0.3.1.dist-info/METADATA
RecFeatureSelect-0.3.1.dist-info/WHEEL
RecFeatureSelect-0.3.1.dist-info/top_level.txt
RecFeatureSelect-0.3.1.dist-info/RECORD
